ctools/__init__.py
ctools/__init__.pyi
ctools/_ctools.cp37-win_amd64.pyd
ctools-0.2.0.dist-info/LICENSE
ctools-0.2.0.dist-info/METADATA
ctools-0.2.0.dist-info/WHEEL
ctools-0.2.0.dist-info/top_level.txt
ctools-0.2.0.dist-info/RECORD
