Metadata-Version: 2.1
Name: ctools
Version: 0.2.0
Summary: A collection of useful extensions for python implement in C.
Home-page: https://github.com/ko-han/python-ctools
Author: hanke
Author-email: hanke0@outlook.com
License: Apache License 2.0
Project-URL: Bug Tracker, https://github.com/ko-han/python-ctools/issues
Project-URL: Documentation, https://python-ctools.readthedocs.io
Project-URL: Source Code, https://github.com/ko-han/python-ctools
Platform: UNKNOWN
Classifier: License :: OSI Approved :: Apache Software License
Classifier: Programming Language :: C
Classifier: Programming Language :: Python
Classifier: Programming Language :: Python :: 3
Classifier: Programming Language :: Python :: 3.5
Classifier: Programming Language :: Python :: 3.6
Classifier: Programming Language :: Python :: 3.7
Classifier: Programming Language :: Python :: 3.8
Classifier: Programming Language :: Python :: Implementation :: CPython
Classifier: Operating System :: OS Independent
Classifier: Operating System :: MacOS
Classifier: Operating System :: Microsoft :: Windows
Classifier: Operating System :: POSIX
Classifier: Operating System :: Unix
Classifier: Topic :: Utilities
Classifier: Topic :: Software Development
Classifier: Development Status :: 5 - Production/Stable
Classifier: Intended Audience :: Developers
Requires-Python: >=3.5
